deltadir/__init__.py
deltadir/__version__.py
deltadir/cli.py
deltadir-0.1.0.dist-info/licenses/LICENSE
deltadir-0.1.0.dist-info/METADATA
deltadir-0.1.0.dist-info/WHEEL
deltadir-0.1.0.dist-info/entry_points.txt
deltadir-0.1.0.dist-info/top_level.txt
deltadir-0.1.0.dist-info/RECORD
