Metadata-Version: 2.4
Name: deltadir
Version: 0.1.0
Summary: Compare directories. Source (src) never modified, dst can be updated with -s/--sync
Author: Your Name
Author-email: you@example.com
License: MIT
Requires-Python: >=3.10
License-File: LICENSE
Dynamic: author
Dynamic: author-email
Dynamic: description
Dynamic: description-content-type
Dynamic: license
Dynamic: license-file
Dynamic: requires-python
Dynamic: summary
